typedcols.py
typedcols-0.1.15.dist-info/LICENSE
typedcols-0.1.15.dist-info/METADATA
typedcols-0.1.15.dist-info/WHEEL
typedcols-0.1.15.dist-info/top_level.txt
typedcols-0.1.15.dist-info/zip-safe
typedcols-0.1.15.dist-info/RECORD
