Metadata-Version: 2.1
Name: typedcols
Version: 0.1.15
Summary: Python library providing typed collections.
Author: Pavel Kacha
Author-email: pavel.kacha@cesnet.cz
License: ISC
Project-URL: Documentation, https://709.gitlab-pages.cesnet.cz/warden/typedcols/master/html/manual.html
Project-URL: Source, https://gitlab.cesnet.cz/709/warden/typedcols
Project-URL: Tracker, https://gitlab.cesnet.cz/709/warden/typedcols/-/issues
Keywords: library
Classifier: Development Status :: 4 - Beta
Classifier: License :: OSI Approved :: ISC License (ISCL)
Classifier: Programming Language :: Python
License-File: LICENSE
